summer/inversion_of_control/__init__.py
summer/inversion_of_control/constants.py
summer/inversion_of_control/dependencies.py
summer/inversion_of_control/service_locator.py
summer/models/__init__.py
summer/models/camel/__init__.py
summer/models/camel/camel_model.py
summer/models/camel/str_to_camel_case.py
summer/patterns/__init__.py
summer/patterns/singleton_meta.py
python_summer_boot-1.0.13.dist-info/LICENSE
python_summer_boot-1.0.13.dist-info/METADATA
python_summer_boot-1.0.13.dist-info/WHEEL
python_summer_boot-1.0.13.dist-info/top_level.txt
python_summer_boot-1.0.13.dist-info/RECORD
